{"meta": {"schemeCode": 106602, "schemeName": "ABN AMRO Interval Fund - Quarterly Plan I - Growth Option - Compulsory Renewal", "ISIN_Div_Payout_or_ISIN_Growth": "NA", "ISIN_Div_Reinvestment": "NA", "amc": "ABN  AMRO Mutual Fund", "category": "Open Ended Schemes ( Income )"}, "data": [{"nav": 11.0593, "repurchasePrice": 10.9487, "salePrice": 11.0593, "date": "07-Nov-2008"}, {"nav": 11.0708, "repurchasePrice": 10.9601, "salePrice": 11.0708, "date": "06-Nov-2008"}, {"nav": 11.067, "repurchasePrice": 10.9563, "salePrice": 11.067, "date": "05-Nov-2008"}, {"nav": 11.063, "repurchasePrice": 10.9524, "salePrice": 11.063, "date": "04-Nov-2008"}, {"nav": 11.059, "repurchasePrice": 10.9484, "salePrice": 11.059, "date": "03-Nov-2008"}, {"nav": 11.074, "repurchasePrice": 10.9633, "salePrice": 11.074, "date": "31-Oct-2008"}, {"nav": 11.0674, "repurchasePrice": 10.9567, "salePrice": 11.0674, "date": "29-Oct-2008"}, {"nav": 11.0621, "repurchasePrice": 10.9515, "salePrice": 11.0621, "date": "27-Oct-2008"}, {"nav": 11.0524, "repurchasePrice": 10.9419, "salePrice": 11.0524, "date": "24-Oct-2008"}, {"nav": 11.0491, "repurchasePrice": 10.9386, "salePrice": 11.0491, "date": "23-Oct-2008"}, {"nav": 11.0459, "repurchasePrice": 10.9354, "salePrice": 11.0459, "date": "22-Oct-2008"}, {"nav": 11.0374, "repurchasePrice": 10.927, "salePrice": 11.0374, "date": "20-Oct-2008"}, {"nav": 11.0272, "repurchasePrice": 10.9169, "salePrice": 11.0272, "date": "17-Oct-2008"}, {"nav": 11.0249, "repurchasePrice": 10.9147, "salePrice": 11.0249, "date": "16-Oct-2008"}, {"nav": 11.0215, "repurchasePrice": 10.9113, "salePrice": 11.0215, "date": "15-Oct-2008"}, {"nav": 11.018, "repurchasePrice": 10.9078, "salePrice": 11.018, "date": "14-Oct-2008"}, {"nav": 11.0467, "repurchasePrice": 10.9362, "salePrice": 11.0467, "date": "13-Oct-2008"}, {"nav": 11.0362, "repurchasePrice": 10.9258, "salePrice": 11.0362, "date": "10-Oct-2008"}, {"nav": 11.0292, "repurchasePrice": 10.9189, "salePrice": 11.0292, "date": "08-Oct-2008"}, {"nav": 11.0257, "repurchasePrice": 10.9154, "salePrice": 11.0257, "date": "07-Oct-2008"}, {"nav": 11.0222, "repurchasePrice": 10.912, "salePrice": 11.0222, "date": "06-Oct-2008"}, {"nav": 11.0117, "repurchasePrice": 10.9016, "salePrice": 11.0117, "date": "03-Oct-2008"}, {"nav": 11.0047, "repurchasePrice": 10.8947, "salePrice": 11.0047, "date": "01-Oct-2008"}, {"nav": 10.9977, "repurchasePrice": 10.8877, "salePrice": 10.9977, "date": "29-Sep-2008"}, {"nav": 10.9873, "repurchasePrice": 10.8774, "salePrice": 10.9873, "date": "26-Sep-2008"}, {"nav": 10.9838, "repurchasePrice": 10.874, "salePrice": 10.9838, "date": "25-Sep-2008"}, {"nav": 10.9803, "repurchasePrice": 10.8705, "salePrice": 10.9803, "date": "24-Sep-2008"}, {"nav": 10.9768, "repurchasePrice": 10.867, "salePrice": 10.9768, "date": "23-Sep-2008"}, {"nav": 10.9733, "repurchasePrice": 10.8636, "salePrice": 10.9733, "date": "22-Sep-2008"}, {"nav": 10.9627, "repurchasePrice": 10.8531, "salePrice": 10.9627, "date": "19-Sep-2008"}, {"nav": 10.9592, "repurchasePrice": 10.8496, "salePrice": 10.9592, "date": "18-Sep-2008"}, {"nav": 10.9558, "repurchasePrice": 10.8462, "salePrice": 10.9558, "date": "17-Sep-2008"}, {"nav": 10.9527, "repurchasePrice": 10.8432, "salePrice": 10.9527, "date": "16-Sep-2008"}, {"nav": 10.9503, "repurchasePrice": 10.8408, "salePrice": 10.9503, "date": "15-Sep-2008"}, {"nav": 10.9429, "repurchasePrice": 10.8335, "salePrice": 10.9429, "date": "12-Sep-2008"}, {"nav": 10.9406, "repurchasePrice": 10.8312, "salePrice": 10.9406, "date": "11-Sep-2008"}, {"nav": 10.9381, "repurchasePrice": 10.8287, "salePrice": 10.9381, "date": "10-Sep-2008"}, {"nav": 10.9355, "repurchasePrice": 10.8261, "salePrice": 10.9355, "date": "09-Sep-2008"}, {"nav": 10.9328, "repurchasePrice": 10.8235, "salePrice": 10.9328, "date": "08-Sep-2008"}, {"nav": 10.9248, "repurchasePrice": 10.8156, "salePrice": 10.9248, "date": "05-Sep-2008"}, {"nav": 10.9221, "repurchasePrice": 10.8129, "salePrice": 10.9221, "date": "04-Sep-2008"}, {"nav": 10.9167, "repurchasePrice": 10.8075, "salePrice": 10.9167, "date": "02-Sep-2008"}, {"nav": 10.914, "repurchasePrice": 10.8049, "salePrice": 10.914, "date": "01-Sep-2008"}, {"nav": 10.906, "repurchasePrice": 10.7969, "salePrice": 10.906, "date": "29-Aug-2008"}, {"nav": 10.9033, "repurchasePrice": 10.7943, "salePrice": 10.9033, "date": "28-Aug-2008"}, {"nav": 10.9006, "repurchasePrice": 10.7916, "salePrice": 10.9006, "date": "27-Aug-2008"}, {"nav": 10.8979, "repurchasePrice": 10.7889, "salePrice": 10.8979, "date": "26-Aug-2008"}, {"nav": 10.8952, "repurchasePrice": 10.7862, "salePrice": 10.8952, "date": "25-Aug-2008"}, {"nav": 10.8871, "repurchasePrice": 10.7782, "salePrice": 10.8871, "date": "22-Aug-2008"}, {"nav": 10.8844, "repurchasePrice": 10.7756, "salePrice": 10.8844, "date": "21-Aug-2008"}, {"nav": 10.8817, "repurchasePrice": 10.7729, "salePrice": 10.8817, "date": "20-Aug-2008"}, {"nav": 10.8763, "repurchasePrice": 10.7675, "salePrice": 10.8763, "date": "18-Aug-2008"}, {"nav": 10.8655, "repurchasePrice": 10.7568, "salePrice": 10.8655, "date": "14-Aug-2008"}, {"nav": 10.8628, "repurchasePrice": 10.7542, "salePrice": 10.8628, "date": "13-Aug-2008"}, {"nav": 10.8601, "repurchasePrice": 10.7515, "salePrice": 10.8601, "date": "12-Aug-2008"}, {"nav": 10.8574, "repurchasePrice": 10.7488, "salePrice": 10.8574, "date": "11-Aug-2008"}, {"nav": 10.8493, "repurchasePrice": 10.7408, "salePrice": 10.8493, "date": "08-Aug-2008"}, {"nav": 10.8466, "repurchasePrice": 10.7381, "salePrice": 10.8466, "date": "07-Aug-2008"}, {"nav": 10.8439, "repurchasePrice": 10.7355, "salePrice": 10.8439, "date": "06-Aug-2008"}, {"nav": 10.8411, "repurchasePrice": 10.7327, "salePrice": 10.8411, "date": "05-Aug-2008"}, {"nav": 10.8384, "repurchasePrice": 10.73, "salePrice": 10.8384, "date": "04-Aug-2008"}, {"nav": 10.8303, "repurchasePrice": 10.722, "salePrice": 10.8303, "date": "01-Aug-2008"}, {"nav": 10.8276, "repurchasePrice": 10.7193, "salePrice": 10.8276, "date": "31-Jul-2008"}, {"nav": 10.8249, "repurchasePrice": 10.7167, "salePrice": 10.8249, "date": "30-Jul-2008"}, {"nav": 10.8221, "repurchasePrice": 10.7139, "salePrice": 10.8221, "date": "29-Jul-2008"}, {"nav": 10.8194, "repurchasePrice": 10.7112, "salePrice": 10.8194, "date": "28-Jul-2008"}, {"nav": 10.8113, "repurchasePrice": 10.7032, "salePrice": 10.8113, "date": "25-Jul-2008"}, {"nav": 10.8086, "repurchasePrice": 10.7005, "salePrice": 10.8086, "date": "24-Jul-2008"}, {"nav": 10.8059, "repurchasePrice": 10.6978, "salePrice": 10.8059, "date": "23-Jul-2008"}, {"nav": 10.8031, "repurchasePrice": 10.6951, "salePrice": 10.8031, "date": "22-Jul-2008"}, {"nav": 10.8004, "repurchasePrice": 10.6924, "salePrice": 10.8004, "date": "21-Jul-2008"}, {"nav": 10.7923, "repurchasePrice": 10.6844, "salePrice": 10.7923, "date": "18-Jul-2008"}, {"nav": 10.7896, "repurchasePrice": 10.6817, "salePrice": 10.7896, "date": "17-Jul-2008"}, {"nav": 10.7869, "repurchasePrice": 10.679, "salePrice": 10.7869, "date": "16-Jul-2008"}, {"nav": 10.7841, "repurchasePrice": 10.6763, "salePrice": 10.7841, "date": "15-Jul-2008"}, {"nav": 10.7814, "repurchasePrice": 10.6736, "salePrice": 10.7814, "date": "14-Jul-2008"}, {"nav": 10.7733, "repurchasePrice": 10.6656, "salePrice": 10.7733, "date": "11-Jul-2008"}, {"nav": 10.7706, "repurchasePrice": 10.6629, "salePrice": 10.7706, "date": "10-Jul-2008"}, {"nav": 10.7679, "repurchasePrice": 10.6602, "salePrice": 10.7679, "date": "09-Jul-2008"}, {"nav": 10.7651, "repurchasePrice": 10.6574, "salePrice": 10.7651, "date": "08-Jul-2008"}, {"nav": 10.7624, "repurchasePrice": 10.6548, "salePrice": 10.7624, "date": "07-Jul-2008"}, {"nav": 10.7543, "repurchasePrice": 10.6468, "salePrice": 10.7543, "date": "04-Jul-2008"}, {"nav": 10.7516, "repurchasePrice": 10.6441, "salePrice": 10.7516, "date": "03-Jul-2008"}, {"nav": 10.7489, "repurchasePrice": 10.6414, "salePrice": 10.7489, "date": "02-Jul-2008"}, {"nav": 10.7434, "repurchasePrice": 10.636, "salePrice": 10.7434, "date": "30-Jun-2008"}, {"nav": 10.7353, "repurchasePrice": 10.6279, "salePrice": 10.7353, "date": "27-Jun-2008"}, {"nav": 10.7326, "repurchasePrice": 10.6253, "salePrice": 10.7326, "date": "26-Jun-2008"}, {"nav": 10.7299, "repurchasePrice": 10.6226, "salePrice": 10.7299, "date": "25-Jun-2008"}, {"nav": 10.7273, "repurchasePrice": 10.62, "salePrice": 10.7273, "date": "24-Jun-2008"}, {"nav": 10.7247, "repurchasePrice": 10.6175, "salePrice": 10.7247, "date": "23-Jun-2008"}, {"nav": 10.717, "repurchasePrice": 10.6098, "salePrice": 10.717, "date": "20-Jun-2008"}, {"nav": 10.7145, "repurchasePrice": 10.6074, "salePrice": 10.7145, "date": "19-Jun-2008"}, {"nav": 10.7121, "repurchasePrice": 10.605, "salePrice": 10.7121, "date": "18-Jun-2008"}, {"nav": 10.7097, "repurchasePrice": 10.6026, "salePrice": 10.7097, "date": "17-Jun-2008"}, {"nav": 10.7074, "repurchasePrice": 10.6003, "salePrice": 10.7074, "date": "16-Jun-2008"}, {"nav": 10.6981, "repurchasePrice": 10.5911, "salePrice": 10.6981, "date": "13-Jun-2008"}, {"nav": 10.6951, "repurchasePrice": 10.5881, "salePrice": 10.6951, "date": "12-Jun-2008"}, {"nav": 10.692, "repurchasePrice": 10.5851, "salePrice": 10.692, "date": "11-Jun-2008"}, {"nav": 10.689, "repurchasePrice": 10.5821, "salePrice": 10.689, "date": "10-Jun-2008"}, {"nav": 10.686, "repurchasePrice": 10.5791, "salePrice": 10.686, "date": "09-Jun-2008"}, {"nav": 10.677, "repurchasePrice": 10.5702, "salePrice": 10.677, "date": "06-Jun-2008"}, {"nav": 10.674, "repurchasePrice": 10.5673, "salePrice": 10.674, "date": "05-Jun-2008"}, {"nav": 10.671, "repurchasePrice": 10.5643, "salePrice": 10.671, "date": "04-Jun-2008"}, {"nav": 10.668, "repurchasePrice": 10.5613, "salePrice": 10.668, "date": "03-Jun-2008"}, {"nav": 10.665, "repurchasePrice": 10.5584, "salePrice": 10.665, "date": "02-Jun-2008"}, {"nav": 10.656, "repurchasePrice": 10.5494, "salePrice": 10.656, "date": "30-May-2008"}, {"nav": 10.653, "repurchasePrice": 10.5465, "salePrice": 10.653, "date": "29-May-2008"}, {"nav": 10.65, "repurchasePrice": 10.5435, "salePrice": 10.65, "date": "28-May-2008"}, {"nav": 10.647, "repurchasePrice": 10.5405, "salePrice": 10.647, "date": "27-May-2008"}, {"nav": 10.6439, "repurchasePrice": 10.5375, "salePrice": 10.6439, "date": "26-May-2008"}, {"nav": 10.6348, "repurchasePrice": 10.5285, "salePrice": 10.6348, "date": "23-May-2008"}, {"nav": 10.6318, "repurchasePrice": 10.5255, "salePrice": 10.6318, "date": "22-May-2008"}, {"nav": 10.6288, "repurchasePrice": 10.5225, "salePrice": 10.6288, "date": "21-May-2008"}, {"nav": 10.6258, "repurchasePrice": 10.5195, "salePrice": 10.6258, "date": "20-May-2008"}, {"nav": 10.6136, "repurchasePrice": 10.5075, "salePrice": 10.6136, "date": "16-May-2008"}, {"nav": 10.6106, "repurchasePrice": 10.5045, "salePrice": 10.6106, "date": "15-May-2008"}, {"nav": 10.6076, "repurchasePrice": 10.5015, "salePrice": 10.6076, "date": "14-May-2008"}, {"nav": 10.6045, "repurchasePrice": 10.4985, "salePrice": 10.6045, "date": "13-May-2008"}, {"nav": 10.6015, "repurchasePrice": 10.4955, "salePrice": 10.6015, "date": "12-May-2008"}, {"nav": 10.5924, "repurchasePrice": 10.4865, "salePrice": 10.5924, "date": "09-May-2008"}, {"nav": 10.5894, "repurchasePrice": 10.4835, "salePrice": 10.5894, "date": "08-May-2008"}, {"nav": 10.5863, "repurchasePrice": 10.4804, "salePrice": 10.5863, "date": "07-May-2008"}, {"nav": 10.5833, "repurchasePrice": 10.4775, "salePrice": 10.5833, "date": "06-May-2008"}, {"nav": 10.5803, "repurchasePrice": 10.4745, "salePrice": 10.5803, "date": "05-May-2008"}, {"nav": 10.5712, "repurchasePrice": 10.4655, "salePrice": 10.5712, "date": "02-May-2008"}, {"nav": 10.5651, "repurchasePrice": 10.4594, "salePrice": 10.5651, "date": "30-Apr-2008"}, {"nav": 10.5621, "repurchasePrice": 10.4565, "salePrice": 10.5621, "date": "29-Apr-2008"}, {"nav": 10.559, "repurchasePrice": 10.4534, "salePrice": 10.559, "date": "28-Apr-2008"}, {"nav": 10.55, "repurchasePrice": 10.4445, "salePrice": 10.55, "date": "25-Apr-2008"}, {"nav": 10.5469, "repurchasePrice": 10.4414, "salePrice": 10.5469, "date": "24-Apr-2008"}, {"nav": 10.5438, "repurchasePrice": 10.4384, "salePrice": 10.5438, "date": "23-Apr-2008"}, {"nav": 10.5407, "repurchasePrice": 10.4353, "salePrice": 10.5407, "date": "22-Apr-2008"}, {"nav": 10.5376, "repurchasePrice": 10.4322, "salePrice": 10.5376, "date": "21-Apr-2008"}, {"nav": 10.5252, "repurchasePrice": 10.4199, "salePrice": 10.5252, "date": "17-Apr-2008"}, {"nav": 10.5221, "repurchasePrice": 10.4169, "salePrice": 10.5221, "date": "16-Apr-2008"}, {"nav": 10.519, "repurchasePrice": 10.4138, "salePrice": 10.519, "date": "15-Apr-2008"}, {"nav": 10.5065, "repurchasePrice": 10.4014, "salePrice": 10.5065, "date": "11-Apr-2008"}, {"nav": 10.5034, "repurchasePrice": 10.3984, "salePrice": 10.5034, "date": "10-Apr-2008"}, {"nav": 10.5003, "repurchasePrice": 10.3953, "salePrice": 10.5003, "date": "09-Apr-2008"}, {"nav": 10.4972, "repurchasePrice": 10.3922, "salePrice": 10.4972, "date": "08-Apr-2008"}, {"nav": 10.4941, "repurchasePrice": 10.3892, "salePrice": 10.4941, "date": "07-Apr-2008"}, {"nav": 10.4848, "repurchasePrice": 10.38, "salePrice": 10.4848, "date": "04-Apr-2008"}, {"nav": 10.4817, "repurchasePrice": 10.3769, "salePrice": 10.4817, "date": "03-Apr-2008"}, {"nav": 10.4786, "repurchasePrice": 10.3738, "salePrice": 10.4786, "date": "02-Apr-2008"}, {"nav": 10.4724, "repurchasePrice": 10.3677, "salePrice": 10.4724, "date": "31-Mar-2008"}, {"nav": 10.463, "repurchasePrice": 10.3584, "salePrice": 10.463, "date": "28-Mar-2008"}, {"nav": 10.4599, "repurchasePrice": 10.3553, "salePrice": 10.4599, "date": "27-Mar-2008"}, {"nav": 10.4571, "repurchasePrice": 10.3525, "salePrice": 10.4571, "date": "26-Mar-2008"}, {"nav": 10.4544, "repurchasePrice": 10.3499, "salePrice": 10.4544, "date": "25-Mar-2008"}, {"nav": 10.4519, "repurchasePrice": 10.3474, "salePrice": 10.4519, "date": "24-Mar-2008"}, {"nav": 10.4394, "repurchasePrice": 10.335, "salePrice": 10.4394, "date": "19-Mar-2008"}, {"nav": 10.4368, "repurchasePrice": 10.3324, "salePrice": 10.4368, "date": "18-Mar-2008"}, {"nav": 10.4387, "repurchasePrice": 10.3343, "salePrice": 10.4387, "date": "17-Mar-2008"}, {"nav": 10.4319, "repurchasePrice": 10.3276, "salePrice": 10.4319, "date": "14-Mar-2008"}, {"nav": 10.4296, "repurchasePrice": 10.3253, "salePrice": 10.4296, "date": "13-Mar-2008"}, {"nav": 10.4273, "repurchasePrice": 10.323, "salePrice": 10.4273, "date": "12-Mar-2008"}, {"nav": 10.425, "repurchasePrice": 10.3208, "salePrice": 10.425, "date": "11-Mar-2008"}, {"nav": 10.4208, "repurchasePrice": 10.3166, "salePrice": 10.4208, "date": "10-Mar-2008"}, {"nav": 10.4129, "repurchasePrice": 10.3088, "salePrice": 10.4129, "date": "07-Mar-2008"}, {"nav": 10.4074, "repurchasePrice": 10.3033, "salePrice": 10.4074, "date": "05-Mar-2008"}, {"nav": 10.4047, "repurchasePrice": 10.3007, "salePrice": 10.4047, "date": "04-Mar-2008"}, {"nav": 10.4019, "repurchasePrice": 10.2979, "salePrice": 10.4019, "date": "03-Mar-2008"}, {"nav": 10.3937, "repurchasePrice": 10.2898, "salePrice": 10.3937, "date": "29-Feb-2008"}, {"nav": 10.3903, "repurchasePrice": 10.2864, "salePrice": 10.3903, "date": "28-Feb-2008"}, {"nav": 10.3876, "repurchasePrice": 10.2837, "salePrice": 10.3876, "date": "27-Feb-2008"}, {"nav": 10.3847, "repurchasePrice": 10.2809, "salePrice": 10.3847, "date": "26-Feb-2008"}, {"nav": 10.3819, "repurchasePrice": 10.2781, "salePrice": 10.3819, "date": "25-Feb-2008"}, {"nav": 10.3741, "repurchasePrice": 10.2704, "salePrice": 10.3741, "date": "22-Feb-2008"}, {"nav": 10.3715, "repurchasePrice": 10.2678, "salePrice": 10.3715, "date": "21-Feb-2008"}, {"nav": 10.3689, "repurchasePrice": 10.2652, "salePrice": 10.3689, "date": "20-Feb-2008"}, {"nav": 10.3664, "repurchasePrice": 10.2627, "salePrice": 10.3664, "date": "19-Feb-2008"}, {"nav": 10.3638, "repurchasePrice": 10.2602, "salePrice": 10.3638, "date": "18-Feb-2008"}, {"nav": 10.3563, "repurchasePrice": 10.2527, "salePrice": 10.3563, "date": "15-Feb-2008"}, {"nav": 10.3538, "repurchasePrice": 10.2503, "salePrice": 10.3538, "date": "14-Feb-2008"}, {"nav": 10.3511, "repurchasePrice": 10.2476, "salePrice": 10.3511, "date": "13-Feb-2008"}, {"nav": 10.3485, "repurchasePrice": 10.245, "salePrice": 10.3485, "date": "12-Feb-2008"}, {"nav": 10.3458, "repurchasePrice": 10.2423, "salePrice": 10.3458, "date": "11-Feb-2008"}, {"nav": 10.338, "repurchasePrice": 10.2346, "salePrice": 10.338, "date": "08-Feb-2008"}, {"nav": 10.3354, "repurchasePrice": 10.232, "salePrice": 10.3354, "date": "07-Feb-2008"}, {"nav": 10.3328, "repurchasePrice": 10.2295, "salePrice": 10.3328, "date": "06-Feb-2008"}, {"nav": 10.3303, "repurchasePrice": 10.227, "salePrice": 10.3303, "date": "05-Feb-2008"}, {"nav": 10.3277, "repurchasePrice": 10.2244, "salePrice": 10.3277, "date": "04-Feb-2008"}, {"nav": 10.318, "repurchasePrice": 10.2148, "salePrice": 10.318, "date": "01-Feb-2008"}, {"nav": 10.3152, "repurchasePrice": 10.212, "salePrice": 10.3152, "date": "31-Jan-2008"}, {"nav": 10.3124, "repurchasePrice": 10.2093, "salePrice": 10.3124, "date": "30-Jan-2008"}, {"nav": 10.3095, "repurchasePrice": 10.2064, "salePrice": 10.3095, "date": "29-Jan-2008"}, {"nav": 10.3066, "repurchasePrice": 10.2035, "salePrice": 10.3066, "date": "28-Jan-2008"}, {"nav": 10.298, "repurchasePrice": 10.195, "salePrice": 10.298, "date": "25-Jan-2008"}, {"nav": 10.2951, "repurchasePrice": 10.1921, "salePrice": 10.2951, "date": "24-Jan-2008"}, {"nav": 10.2922, "repurchasePrice": 10.1893, "salePrice": 10.2922, "date": "23-Jan-2008"}, {"nav": 10.2892, "repurchasePrice": 10.1863, "salePrice": 10.2892, "date": "22-Jan-2008"}, {"nav": 10.2864, "repurchasePrice": 10.1835, "salePrice": 10.2864, "date": "21-Jan-2008"}, {"nav": 10.2785, "repurchasePrice": 10.1757, "salePrice": 10.2785, "date": "18-Jan-2008"}, {"nav": 10.276, "repurchasePrice": 10.1732, "salePrice": 10.276, "date": "17-Jan-2008"}, {"nav": 10.2736, "repurchasePrice": 10.1709, "salePrice": 10.2736, "date": "16-Jan-2008"}, {"nav": 10.2712, "repurchasePrice": 10.1685, "salePrice": 10.2712, "date": "15-Jan-2008"}, {"nav": 10.2687, "repurchasePrice": 10.166, "salePrice": 10.2687, "date": "14-Jan-2008"}, {"nav": 10.2614, "repurchasePrice": 10.1588, "salePrice": 10.2614, "date": "11-Jan-2008"}, {"nav": 10.259, "repurchasePrice": 10.1564, "salePrice": 10.259, "date": "10-Jan-2008"}, {"nav": 10.2566, "repurchasePrice": 10.154, "salePrice": 10.2566, "date": "09-Jan-2008"}, {"nav": 10.2543, "repurchasePrice": 10.1518, "salePrice": 10.2543, "date": "08-Jan-2008"}, {"nav": 10.252, "repurchasePrice": 10.1495, "salePrice": 10.252, "date": "07-Jan-2008"}, {"nav": 10.245, "repurchasePrice": 10.1426, "salePrice": 10.245, "date": "04-Jan-2008"}, {"nav": 10.2427, "repurchasePrice": 10.1403, "salePrice": 10.2427, "date": "03-Jan-2008"}, {"nav": 10.2404, "repurchasePrice": 10.138, "salePrice": 10.2404, "date": "02-Jan-2008"}, {"nav": 10.238, "repurchasePrice": 10.1356, "salePrice": 10.238, "date": "01-Jan-2008"}, {"nav": 10.2357, "repurchasePrice": 10.1333, "salePrice": 10.2357, "date": "31-Dec-2007"}, {"nav": 10.2287, "repurchasePrice": 10.1264, "salePrice": 10.2287, "date": "28-Dec-2007"}, {"nav": 10.2264, "repurchasePrice": 10.1241, "salePrice": 10.2264, "date": "27-Dec-2007"}, {"nav": 10.2241, "repurchasePrice": 10.1219, "salePrice": 10.2241, "date": "26-Dec-2007"}, {"nav": 10.2195, "repurchasePrice": 10.1173, "salePrice": 10.2195, "date": "24-Dec-2007"}, {"nav": 10.2102, "repurchasePrice": 10.1081, "salePrice": 10.2102, "date": "20-Dec-2007"}, {"nav": 10.2079, "repurchasePrice": 10.1058, "salePrice": 10.2079, "date": "19-Dec-2007"}, {"nav": 10.2056, "repurchasePrice": 10.1035, "salePrice": 10.2056, "date": "18-Dec-2007"}, {"nav": 10.2033, "repurchasePrice": 10.1013, "salePrice": 10.2033, "date": "17-Dec-2007"}, {"nav": 10.1965, "repurchasePrice": 10.0945, "salePrice": 10.1965, "date": "14-Dec-2007"}, {"nav": 10.1942, "repurchasePrice": 10.0923, "salePrice": 10.1942, "date": "13-Dec-2007"}, {"nav": 10.1919, "repurchasePrice": 10.09, "salePrice": 10.1919, "date": "12-Dec-2007"}, {"nav": 10.1896, "repurchasePrice": 10.0877, "salePrice": 10.1896, "date": "11-Dec-2007"}, {"nav": 10.1873, "repurchasePrice": 10.0854, "salePrice": 10.1873, "date": "10-Dec-2007"}, {"nav": 10.1805, "repurchasePrice": 10.0787, "salePrice": 10.1805, "date": "07-Dec-2007"}, {"nav": 10.1782, "repurchasePrice": 10.0764, "salePrice": 10.1782, "date": "06-Dec-2007"}, {"nav": 10.1759, "repurchasePrice": 10.0741, "salePrice": 10.1759, "date": "05-Dec-2007"}, {"nav": 10.1737, "repurchasePrice": 10.072, "salePrice": 10.1737, "date": "04-Dec-2007"}, {"nav": 10.1714, "repurchasePrice": 10.0697, "salePrice": 10.1714, "date": "03-Dec-2007"}, {"nav": 10.1645, "repurchasePrice": 10.0629, "salePrice": 10.1645, "date": "30-Nov-2007"}, {"nav": 10.1622, "repurchasePrice": 10.0606, "salePrice": 10.1622, "date": "29-Nov-2007"}, {"nav": 10.16, "repurchasePrice": 10.0584, "salePrice": 10.16, "date": "28-Nov-2007"}, {"nav": 10.1577, "repurchasePrice": 10.0561, "salePrice": 10.1577, "date": "27-Nov-2007"}, {"nav": 10.1554, "repurchasePrice": 10.0538, "salePrice": 10.1554, "date": "26-Nov-2007"}, {"nav": 10.1486, "repurchasePrice": 10.0471, "salePrice": 10.1486, "date": "23-Nov-2007"}, {"nav": 10.1463, "repurchasePrice": 10.0448, "salePrice": 10.1463, "date": "22-Nov-2007"}, {"nav": 10.144, "repurchasePrice": 10.0426, "salePrice": 10.144, "date": "21-Nov-2007"}, {"nav": 10.1417, "repurchasePrice": 10.0403, "salePrice": 10.1417, "date": "20-Nov-2007"}, {"nav": 10.1394, "repurchasePrice": 10.038, "salePrice": 10.1394, "date": "19-Nov-2007"}, {"nav": 10.1326, "repurchasePrice": 10.0313, "salePrice": 10.1326, "date": "16-Nov-2007"}, {"nav": 10.1303, "repurchasePrice": 10.029, "salePrice": 10.1303, "date": "15-Nov-2007"}, {"nav": 10.128, "repurchasePrice": 10.0267, "salePrice": 10.128, "date": "14-Nov-2007"}, {"nav": 10.1257, "repurchasePrice": 10.0244, "salePrice": 10.1257, "date": "13-Nov-2007"}, {"nav": 10.1235, "repurchasePrice": 10.0223, "salePrice": 10.1235, "date": "12-Nov-2007"}, {"nav": 10.1143, "repurchasePrice": 10.0132, "salePrice": 10.1143, "date": "08-Nov-2007"}, {"nav": 10.112, "repurchasePrice": 10.0109, "salePrice": 10.112, "date": "07-Nov-2007"}, {"nav": 10.1098, "repurchasePrice": 10.0087, "salePrice": 10.1098, "date": "06-Nov-2007"}, {"nav": 10.1075, "repurchasePrice": 10.0064, "salePrice": 10.1075, "date": "05-Nov-2007"}, {"nav": 10.1006, "repurchasePrice": 9.9996, "salePrice": 10.1006, "date": "02-Nov-2007"}, {"nav": 10.0982, "repurchasePrice": 9.9972, "salePrice": 10.0982, "date": "01-Nov-2007"}, {"nav": 10.0959, "repurchasePrice": 9.9949, "salePrice": 10.0959, "date": "31-Oct-2007"}, {"nav": 10.0937, "repurchasePrice": 9.9928, "salePrice": 10.0937, "date": "30-Oct-2007"}, {"nav": 10.0914, "repurchasePrice": 9.9905, "salePrice": 10.0914, "date": "29-Oct-2007"}, {"nav": 10.0845, "repurchasePrice": 9.9837, "salePrice": 10.0845, "date": "26-Oct-2007"}, {"nav": 10.0822, "repurchasePrice": 9.9814, "salePrice": 10.0822, "date": "25-Oct-2007"}, {"nav": 10.08, "repurchasePrice": 9.9792, "salePrice": 10.08, "date": "24-Oct-2007"}, {"nav": 10.0777, "repurchasePrice": 9.9769, "salePrice": 10.0777, "date": "23-Oct-2007"}, {"nav": 10.0754, "repurchasePrice": 9.9746, "salePrice": 10.0754, "date": "22-Oct-2007"}, {"nav": 10.0685, "repurchasePrice": 9.9678, "salePrice": 10.0685, "date": "19-Oct-2007"}, {"nav": 10.0662, "repurchasePrice": 9.9655, "salePrice": 10.0662, "date": "18-Oct-2007"}, {"nav": 10.064, "repurchasePrice": 9.9634, "salePrice": 10.064, "date": "17-Oct-2007"}, {"nav": 10.0617, "repurchasePrice": 9.9611, "salePrice": 10.0617, "date": "16-Oct-2007"}, {"nav": 10.0594, "repurchasePrice": 9.9588, "salePrice": 10.0594, "date": "15-Oct-2007"}, {"nav": 10.0525, "repurchasePrice": 9.952, "salePrice": 10.0525, "date": "12-Oct-2007"}, {"nav": 10.0502, "repurchasePrice": 9.9497, "salePrice": 10.0502, "date": "11-Oct-2007"}, {"nav": 10.048, "repurchasePrice": 9.9475, "salePrice": 10.048, "date": "10-Oct-2007"}, {"nav": 10.0457, "repurchasePrice": 9.9452, "salePrice": 10.0457, "date": "09-Oct-2007"}, {"nav": 10.0434, "repurchasePrice": 9.943, "salePrice": 10.0434, "date": "08-Oct-2007"}, {"nav": 10.0365, "repurchasePrice": 9.9361, "salePrice": 10.0365, "date": "05-Oct-2007"}, {"nav": 10.0343, "repurchasePrice": 9.934, "salePrice": 10.0343, "date": "04-Oct-2007"}, {"nav": 10.032, "repurchasePrice": 9.9317, "salePrice": 10.032, "date": "03-Oct-2007"}, {"nav": 10.0274, "repurchasePrice": 9.9271, "salePrice": 10.0274, "date": "01-Oct-2007"}, {"nav": 10.0228, "repurchasePrice": 9.9226, "salePrice": 10.0228, "date": "29-Sep-2007"}, {"nav": 10.0205, "repurchasePrice": 9.9203, "salePrice": 10.0205, "date": "28-Sep-2007"}, {"nav": 10.0182, "repurchasePrice": 9.918, "salePrice": 10.0182, "date": "27-Sep-2007"}, {"nav": 10.0159, "repurchasePrice": 9.9157, "salePrice": 10.0159, "date": "26-Sep-2007"}, {"nav": 10.0136, "repurchasePrice": 9.9135, "salePrice": 10.0136, "date": "25-Sep-2007"}, {"nav": 10.0113, "repurchasePrice": 9.9112, "salePrice": 10.0113, "date": "24-Sep-2007"}]}