{"meta": {"schemeCode": 146438, "schemeName": "Navi 3 in 1 Fund - Regular Plan - Half Yearly IDCW", "ISIN_Div_Payout_or_ISIN_Growth": "INF959L01FL1", "ISIN_Div_Reinvestment": "INF959L01FM9", "amc": "Navi Mutual Fund", "category": "Open Ended Schemes ( Hybrid Scheme - Multi Asset Allocation )"}, "data": [{"nav": 19.8071, "repurchasePrice": "NA", "salePrice": "NA", "date": "24-Nov-2020"}, {"nav": 19.7335, "repurchasePrice": "NA", "salePrice": "NA", "date": "23-Nov-2020"}, {"nav": 19.612, "repurchasePrice": "NA", "salePrice": "NA", "date": "20-Nov-2020"}, {"nav": 19.4778, "repurchasePrice": "NA", "salePrice": "NA", "date": "19-Nov-2020"}, {"nav": 19.6796, "repurchasePrice": "NA", "salePrice": "NA", "date": "18-Nov-2020"}, {"nav": 19.6388, "repurchasePrice": "NA", "salePrice": "NA", "date": "17-Nov-2020"}, {"nav": 19.423, "repurchasePrice": "NA", "salePrice": "NA", "date": "13-Nov-2020"}, {"nav": 19.302, "repurchasePrice": "NA", "salePrice": "NA", "date": "12-Nov-2020"}, {"nav": 19.3325, "repurchasePrice": "NA", "salePrice": "NA", "date": "11-Nov-2020"}, {"nav": 19.1642, "repurchasePrice": "NA", "salePrice": "NA", "date": "10-Nov-2020"}, {"nav": 19.2508, "repurchasePrice": "NA", "salePrice": "NA", "date": "09-Nov-2020"}, {"nav": 19.0091, "repurchasePrice": "NA", "salePrice": "NA", "date": "06-Nov-2020"}, {"nav": 18.8308, "repurchasePrice": "NA", "salePrice": "NA", "date": "05-Nov-2020"}, {"nav": 18.613, "repurchasePrice": "NA", "salePrice": "NA", "date": "04-Nov-2020"}, {"nav": 18.4482, "repurchasePrice": "NA", "salePrice": "NA", "date": "03-Nov-2020"}, {"nav": 18.323, "repurchasePrice": "NA", "salePrice": "NA", "date": "02-Nov-2020"}, {"nav": 18.332, "repurchasePrice": "NA", "salePrice": "NA", "date": "30-Oct-2020"}, {"nav": 18.3726, "repurchasePrice": "NA", "salePrice": "NA", "date": "29-Oct-2020"}, {"nav": 18.4042, "repurchasePrice": "NA", "salePrice": "NA", "date": "28-Oct-2020"}, {"nav": 18.561, "repurchasePrice": "NA", "salePrice": "NA", "date": "27-Oct-2020"}, {"nav": 18.3568, "repurchasePrice": "NA", "salePrice": "NA", "date": "26-Oct-2020"}, {"nav": 18.5333, "repurchasePrice": "NA", "salePrice": "NA", "date": "23-Oct-2020"}, {"nav": 18.5229, "repurchasePrice": "NA", "salePrice": "NA", "date": "22-Oct-2020"}, {"nav": 18.559, "repurchasePrice": "NA", "salePrice": "NA", "date": "21-Oct-2020"}, {"nav": 18.5283, "repurchasePrice": "NA", "salePrice": "NA", "date": "20-Oct-2020"}, {"nav": 18.477, "repurchasePrice": "NA", "salePrice": "NA", "date": "19-Oct-2020"}, {"nav": 18.3946, "repurchasePrice": "NA", "salePrice": "NA", "date": "16-Oct-2020"}, {"nav": 18.2989, "repurchasePrice": "NA", "salePrice": "NA", "date": "15-Oct-2020"}, {"nav": 18.5638, "repurchasePrice": "NA", "salePrice": "NA", "date": "14-Oct-2020"}, {"nav": 18.5898, "repurchasePrice": "NA", "salePrice": "NA", "date": "13-Oct-2020"}, {"nav": 18.6017, "repurchasePrice": "NA", "salePrice": "NA", "date": "12-Oct-2020"}, {"nav": 18.569, "repurchasePrice": "NA", "salePrice": "NA", "date": "09-Oct-2020"}, {"nav": 18.4904, "repurchasePrice": "NA", "salePrice": "NA", "date": "08-Oct-2020"}, {"nav": 18.3877, "repurchasePrice": "NA", "salePrice": "NA", "date": "07-Oct-2020"}, {"nav": 18.3989, "repurchasePrice": "NA", "salePrice": "NA", "date": "06-Oct-2020"}, {"nav": 18.2965, "repurchasePrice": "NA", "salePrice": "NA", "date": "05-Oct-2020"}, {"nav": 18.2192, "repurchasePrice": "NA", "salePrice": "NA", "date": "01-Oct-2020"}, {"nav": 18.1177, "repurchasePrice": "NA", "salePrice": "NA", "date": "30-Sep-2020"}, {"nav": 18.0682, "repurchasePrice": "NA", "salePrice": "NA", "date": "29-Sep-2020"}, {"nav": 18.0763, "repurchasePrice": "NA", "salePrice": "NA", "date": "28-Sep-2020"}, {"nav": 17.9091, "repurchasePrice": "NA", "salePrice": "NA", "date": "25-Sep-2020"}, {"nav": 17.632, "repurchasePrice": "NA", "salePrice": "NA", "date": "24-Sep-2020"}, {"nav": 17.9823, "repurchasePrice": "NA", "salePrice": "NA", "date": "23-Sep-2020"}, {"nav": 18.0161, "repurchasePrice": "NA", "salePrice": "NA", "date": "22-Sep-2020"}, {"nav": 18.1369, "repurchasePrice": "NA", "salePrice": "NA", "date": "21-Sep-2020"}, {"nav": 18.4871, "repurchasePrice": "NA", "salePrice": "NA", "date": "18-Sep-2020"}, {"nav": 18.3878, "repurchasePrice": "NA", "salePrice": "NA", "date": "17-Sep-2020"}, {"nav": 18.4396, "repurchasePrice": "NA", "salePrice": "NA", "date": "16-Sep-2020"}, {"nav": 18.3287, "repurchasePrice": "NA", "salePrice": "NA", "date": "15-Sep-2020"}, {"nav": 18.1912, "repurchasePrice": "NA", "salePrice": "NA", "date": "14-Sep-2020"}, {"nav": 18.0893, "repurchasePrice": "NA", "salePrice": "NA", "date": "11-Sep-2020"}, {"nav": 18.0612, "repurchasePrice": "NA", "salePrice": "NA", "date": "10-Sep-2020"}, {"nav": 17.925, "repurchasePrice": "NA", "salePrice": "NA", "date": "09-Sep-2020"}, {"nav": 17.8947, "repurchasePrice": "NA", "salePrice": "NA", "date": "08-Sep-2020"}, {"nav": 17.9134, "repurchasePrice": "NA", "salePrice": "NA", "date": "07-Sep-2020"}, {"nav": 17.9581, "repurchasePrice": "NA", "salePrice": "NA", "date": "04-Sep-2020"}, {"nav": 18.1546, "repurchasePrice": "NA", "salePrice": "NA", "date": "03-Sep-2020"}, {"nav": 18.1776, "repurchasePrice": "NA", "salePrice": "NA", "date": "02-Sep-2020"}, {"nav": 18.083, "repurchasePrice": "NA", "salePrice": "NA", "date": "01-Sep-2020"}, {"nav": 17.9433, "repurchasePrice": "NA", "salePrice": "NA", "date": "31-Aug-2020"}, {"nav": 18.2817, "repurchasePrice": "NA", "salePrice": "NA", "date": "28-Aug-2020"}, {"nav": 18.2618, "repurchasePrice": "NA", "salePrice": "NA", "date": "27-Aug-2020"}, {"nav": 18.2751, "repurchasePrice": "NA", "salePrice": "NA", "date": "26-Aug-2020"}, {"nav": 18.2056, "repurchasePrice": "NA", "salePrice": "NA", "date": "25-Aug-2020"}, {"nav": 18.2087, "repurchasePrice": "NA", "salePrice": "NA", "date": "24-Aug-2020"}]}